{
	"info": {
		"_postman_id": "9f4dea56-a378-404a-85bc-27a857d8c107",
		"name": "Lavarel Bookstore 2021",
		"schema": "https://schema.getpostman.com/json/collection/v2.1.0/collection.json"
	},
	"item": [
		{
			"name": "Get all Books",
			"request": {
				"method": "GET",
				"header": [
					{
						"key": "Content-Type",
						"value": "application/json",
						"type": "text"
					},
					{
						"key": "Accept",
						"value": "application/json",
						"type": "text"
					}
				],
				"url": {
					"raw": "https://bookstore21.putz.kwmhgb.at/api/books",
					"protocol": "https",
					"host": [
						"bookstore21",
						"putz",
						"kwmhgb",
						"at"
					],
					"path": [
						"api",
						"books"
					]
				}
			},
			"response": []
		},
		{
			"name": "Find Book by ISBN",
			"request": {
				"method": "GET",
				"header": [
					{
						"key": "Content-Type",
						"value": "application/json",
						"type": "text"
					},
					{
						"key": "Accept",
						"value": "application/json",
						"type": "text"
					}
				],
				"url": {
					"raw": "https://bookstore21.putz.kwmhgb.at/api/book/2394823948234",
					"protocol": "https",
					"host": [
						"bookstore21",
						"putz",
						"kwmhgb",
						"at"
					],
					"path": [
						"api",
						"book",
						"2394823948234"
					]
				}
			},
			"response": []
		},
		{
			"name": "Check ISBN",
			"request": {
				"method": "GET",
				"header": [
					{
						"key": "Accept",
						"value": "application/json",
						"type": "text"
					},
					{
						"key": "Content-Type",
						"value": "application/json",
						"type": "text"
					}
				],
				"url": {
					"raw": "https://bookstore21.putz.kwmhgb.at/api/book/checkisbn/adfasdf",
					"protocol": "https",
					"host": [
						"bookstore21",
						"putz",
						"kwmhgb",
						"at"
					],
					"path": [
						"api",
						"book",
						"checkisbn",
						"adfasdf"
					]
				}
			},
			"response": []
		},
		{
			"name": "Find By Search Term",
			"request": {
				"method": "GET",
				"header": [
					{
						"key": "Accept",
						"value": "application/json",
						"type": "text"
					},
					{
						"key": "Content-Type",
						"value": "application/json",
						"type": "text"
					}
				],
				"url": {
					"raw": "https://bookstore21.putz.kwmhgb.at/api/books/search/Herr der Ringe",
					"protocol": "https",
					"host": [
						"bookstore21",
						"putz",
						"kwmhgb",
						"at"
					],
					"path": [
						"api",
						"books",
						"search",
						"Herr der Ringe"
					]
				}
			},
			"response": []
		},
		{
			"name": "Update Book",
			"request": {
				"method": "PUT",
				"header": [
					{
						"key": "Accept",
						"value": "application/json",
						"type": "text"
					},
					{
						"key": "Content-Type",
						"value": "application/json",
						"type": "text"
					}
				],
				"body": {
					"mode": "raw",
					"raw": " {\n        \"isbn\": \"9394823948234\",\n        \"title\": \"Herr der Ringe UPDATE\",\n        \"subtitle\": \"sdlfkj asldfjasldfk\",\n        \"published\": \"2021-03-12\",\n        \"rating\": 10,\n        \"user_id\": 1, \n        \"description\": \"aldkfjasf aldkjfas\",\n        \"authors\": [\n            {\n                \"id\": 1,\n                \"firstName\": \"Fritz\",\n                \"lastName\": \"Huber\"\n            }\n        ],\n        \"images\": [\n            {\n                \"url\": \"https://m.media-amazon.com/images/I/A1H0tY2Se7L._AC_UY218_.jpg\",\n                \"title\": \"Bild 1 Update\"\n            },\n            {\n                \"url\": \"https://m.media-amazon.com/images/I/A1H0tY2Se7L._AC_UY218_.jpg\",\n                \"title\": \"Bild 2\"\n            }\n        ]\n        \n    }"
				},
				"url": {
					"raw": "https://bookstore21.putz.kwmhgb.at/api/book/9394823948234",
					"protocol": "https",
					"host": [
						"bookstore21",
						"putz",
						"kwmhgb",
						"at"
					],
					"path": [
						"api",
						"book",
						"9394823948234"
					]
				}
			},
			"response": []
		},
		{
			"name": "Save Book",
			"request": {
				"method": "POST",
				"header": [
					{
						"key": "Accept",
						"value": "application/json",
						"type": "text"
					},
					{
						"key": "Content-Type",
						"value": "application/json",
						"type": "text"
					}
				],
				"body": {
					"mode": "raw",
					"raw": " {\n        \"isbn\": \"8394823948234\",\n        \"title\": \"Herr der Ringe \",\n        \"subtitle\": \"sdlfkj asldfjasldfk\",\n        \"published\": \"2021-03-12\",\n        \"rating\": 10,\n        \"user_id\": 1, \n        \"description\": \"aldkfjasf aldkjfas\",\n        \"authors\": [\n            {\n                \"firstName\": \"Fritz\",\n                \"lastName\": \"Huber\"\n            }\n        ],\n        \"images\": [\n            {\n                \"url\": \"https://m.media-amazon.com/images/I/A1H0tY2Se7L._AC_UY218_.jpg\",\n                \"title\": \"Bild 1 Update\"\n            },\n            {\n                \"url\": \"https://m.media-amazon.com/images/I/A1H0tY2Se7L._AC_UY218_.jpg\",\n                \"title\": \"Bild 2\"\n            }\n        ]\n        \n    }"
				},
				"url": {
					"raw": "https://bookstore21.putz.kwmhgb.at/api/book",
					"protocol": "https",
					"host": [
						"bookstore21",
						"putz",
						"kwmhgb",
						"at"
					],
					"path": [
						"api",
						"book"
					]
				}
			},
			"response": []
		},
		{
			"name": "Delete Book",
			"request": {
				"method": "DELETE",
				"header": [
					{
						"key": "Accept",
						"value": "application/json",
						"type": "text"
					},
					{
						"key": "Content-Type",
						"value": "application/json",
						"type": "text"
					}
				],
				"body": {
					"mode": "raw",
					"raw": ""
				},
				"url": {
					"raw": "https://bookstore21.putz.kwmhgb.at/api/book/9394823948234",
					"protocol": "https",
					"host": [
						"bookstore21",
						"putz",
						"kwmhgb",
						"at"
					],
					"path": [
						"api",
						"book",
						"9394823948234"
					]
				}
			},
			"response": []
		}
	]
}